pyabsorb/__init__.py
pyabsorb/azazel.py
pyabsorb/brencon.dat
pyabsorb/brenconff.dat
pyabsorb/lmnts.py
pyabsorb/utils.py
pyabsorb-0.7.dist-info/LICENSE.txt
pyabsorb-0.7.dist-info/METADATA
pyabsorb-0.7.dist-info/WHEEL
pyabsorb-0.7.dist-info/entry_points.txt
pyabsorb-0.7.dist-info/top_level.txt
pyabsorb-0.7.dist-info/RECORD
