Metadata-Version: 2.1
Name: pyabsorb
Version: 0.7
Summary: Calculate X-ray transmission
Author: steche
Author-email: scr10438@gmx.ca
License-File: LICENSE.txt
